currconv/currconv.py
currconv/__init__.py
currconv-0.1.dist-info/METADATA
currconv-0.1.dist-info/DESCRIPTION.rst
currconv-0.1.dist-info/metadata.json
currconv-0.1.dist-info/entry_points.txt
currconv-0.1.dist-info/top_level.txt
currconv-0.1.dist-info/RECORD
currconv-0.1.dist-info/WHEEL
