Metadata-Version: 2.0
Name: currconv
Version: 0.1
Summary: Currency Converter for terminal.
Home-page: https://github.com/conormdurkan/CurrConv
Author: UNKNOWN
Author-email: conormdurkan@gmail.com
License: UNKNOWN
Platform: UNKNOWN
Classifier: License :: OSI Approved :: MIT License
Classifier: Programming Language :: Python :: 3
Classifier: Programming Language :: Python :: 3.2
Classifier: Programming Language :: Python :: 3.3
Classifier: Programming Language :: Python :: 3.4
Requires-Dist: setuptools
Requires-Dist: argparse
Requires-Dist: nose
Requires-Dist: yahoo-finance
